wsqlite3/__init__.py
wsqlite3/__main__.py
wsqlite3/service.py
wsqlite3/verbose_service.py
wsqlite3/_cli/__init__.py
wsqlite3/_cli/argp.py
wsqlite3/_cli/servreg.py
wsqlite3/_cli/logs/__init__.py
wsqlite3/baseclient/__init__.py
wsqlite3/baseclient/baseclient.py
wsqlite3/baseclient/orderutil.py
wsqlite3-0.7.3.dist-info/licenses/LICENSE
wsqlite3-0.7.3.dist-info/METADATA
wsqlite3-0.7.3.dist-info/WHEEL
wsqlite3-0.7.3.dist-info/entry_points.txt
wsqlite3-0.7.3.dist-info/top_level.txt
wsqlite3-0.7.3.dist-info/RECORD
