Metadata-Version: 2.4
Name: wsqlite3
Version: 0.7.3
Summary: WSQLite3 (WebSocket SQLite3) is a simple and lightweight solution to manage access from multiple processes (or threads) to SQLite3 databases.
Author-email: "Adrian F. Hoefflin" <srccircumflex@outlook.com>
License: MIT License
Project-URL: Documentation, https://srccircumflex.github.io/wsqlite3
Project-URL: Repository, https://github.com/srccircumflex/wsqlite3
Keywords: sql,sqlite,sqlite3,threadsave,database server,database service,session manager,websocket,wsqlite3,sqlite3 threadsave,threadsave sqlite3
Classifier: Topic :: Database
Classifier: Topic :: Database :: Database Engines/Servers
Classifier: Programming Language :: Python :: 3.10
Classifier: Programming Language :: Python :: 3.11
Classifier: Programming Language :: Python :: 3.12
Classifier: Programming Language :: Python :: 3.13
Classifier: Programming Language :: Python :: 3.14
Requires-Python: >=3.10
License-File: LICENSE
Requires-Dist: wsdatautil>=1.1
Dynamic: license-file
